feedler/__init__.py
feedler/__meta__.py
feedler/constants.py
feedler/exceptions.py
feedler/parsers.py
feedler/rss.py
feedler/utils.py
feedler-0.0.2.dist-info/LICENSE
feedler-0.0.2.dist-info/METADATA
feedler-0.0.2.dist-info/WHEEL
feedler-0.0.2.dist-info/top_level.txt
feedler-0.0.2.dist-info/RECORD
